tuk/logging/__init__.py
tuk/logging/formatter.py
tuk/logging/logger.py
tuk/logging/traceback.py
tuk/logging/verbose.py
tuk_logging-0.1.0.2025121800.dist-info/licenses/LICENSE
tuk_logging-0.1.0.2025121800.dist-info/METADATA
tuk_logging-0.1.0.2025121800.dist-info/WHEEL
tuk_logging-0.1.0.2025121800.dist-info/top_level.txt
tuk_logging-0.1.0.2025121800.dist-info/RECORD
