Metadata-Version: 2.4
Name: tuk-logging
Version: 0.1.0.2025121800
Summary: TUK Logging Package
Home-page: https://github.com/Tarcadia/tuk-logging
Author: Tarcadia
Author-email: dont@email.me
License: MIT
Project-URL: Bug Reports, https://github.com/Tarcadia/tuk-logging/issues
Project-URL: Source, https://github.com/Tarcadia/tuk-logging
Keywords: logging,log,tuk
Classifier: Development Status :: 2 - Pre-Alpha
Classifier: Intended Audience :: Developers
Classifier: Programming Language :: Python :: 3.11
Classifier: Operating System :: OS Independent
Classifier: Typing :: Typed
Requires-Python: >=3.11
License-File: LICENSE
Dynamic: author
Dynamic: author-email
Dynamic: classifier
Dynamic: description
Dynamic: description-content-type
Dynamic: home-page
Dynamic: keywords
Dynamic: license
Dynamic: license-file
Dynamic: project-url
Dynamic: requires-python
Dynamic: summary
